LICENSE
MANIFEST.in
README.md
setup.py
argresolver/__init__.py
argresolver/resolver.py
argresolver/utils.py
argresolver.egg-info/PKG-INFO
argresolver.egg-info/SOURCES.txt
argresolver.egg-info/dependency_links.txt
argresolver.egg-info/top_level.txt
examples/chain/fallback.py
examples/environment/connect.py
examples/environment/connection.py
examples/map/override_default.py
tests/__init__.py
tests/context.py
tests/test_utils.py