Metadata-Version: 2.1
Name: argresolver
Version: 0.3.1
Summary: Resolve missing arguments at runtime
Home-page: https://github.com/HazardDede/argresolver
Author: d.muth
Author-email: d.muth@gmx.net
License: MIT
Project-URL: Documentation, https://github.com/HazardDede/argresolver/blob/master/README.md
Project-URL: Source, https://github.com/HazardDede/argresolver/
Project-URL: Tracker, https://github.com/HazardDede/argresolver/issues
Keywords: args arguments injection resolve resolver
Platform: UNKNOWN
Classifier: Development Status :: 3 - Alpha
Classifier: Intended Audience :: Developers
Classifier: Topic :: Software Development :: Libraries
Classifier: License :: OSI Approved :: MIT License
Classifier: Programming Language :: Python :: 3.4
Classifier: Programming Language :: Python :: 3.5
Classifier: Programming Language :: Python :: 3.6
Requires-Python: >=3.4
